wssf.py
wssf-6.0.0.dist-info/METADATA
wssf-6.0.0.dist-info/WHEEL
wssf-6.0.0.dist-info/entry_points.txt
wssf-6.0.0.dist-info/RECORD
