Metadata-Version: 2.4
Name: wssf
Version: 6.0.0
Summary: Wenshushu Enhanced CLI Tool - A feature-rich command-line tool for file sharing
Author: JianMoP
Requires-Python: >=3.8
Requires-Dist: base58>=1.0.3
Requires-Dist: pycryptodomex>=3.10.0
Requires-Dist: requests>=2.31.0
